Metadata-Version: 2.4
Name: tempfilerepr
Version: 1.1.3
Summary: Encoder and decoder for the temp encoding.
Home-page: https://t.me/NasrPy
Author: Nasr
Author-email: nasr2python@gmail.com
Classifier: Programming Language :: Python :: 3
Classifier: License :: OSI Approved :: MIT License
Classifier: Operating System :: OS Independent
Requires-Python: >=3.6
Dynamic: author
Dynamic: author-email
Dynamic: classifier
Dynamic: description
Dynamic: description-content-type
Dynamic: home-page
Dynamic: requires-python
Dynamic: summary
